wxpusher/__init__.py
wxpusher/exceptions.py
wxpusher/wxpusher.py
wxpusher/tests/__init__.py
wxpusher/tests/config.sample.py
wxpusher/tests/exceptions.py
wxpusher/tests/test_create_qrcode.py
wxpusher/tests/test_query_message.py
wxpusher/tests/test_query_user.py
wxpusher/tests/test_send_message.py
wxpusher-2.3.0.dist-info/LICENSE
wxpusher-2.3.0.dist-info/METADATA
wxpusher-2.3.0.dist-info/WHEEL
wxpusher-2.3.0.dist-info/top_level.txt
wxpusher-2.3.0.dist-info/RECORD
