Metadata-Version: 2.1
Name: wxpusher
Version: 2.3.0
Summary: WxPusher Python SDK.
Home-page: https://github.com/wxpusher/wxpusher-sdk-python
Author: Xuan (Sean) Hu
Author-email: i+wxpusher@huxuan.org
License: Apache License 2.0
Keywords: wxpusher wechat weixin notification push-notification python-sdk
Platform: UNKNOWN
Classifier: Development Status :: 4 - Beta
Classifier: Intended Audience :: Developers
Classifier: License :: OSI Approved :: Apache Software License
Classifier: Programming Language :: Python :: 3
Classifier: Programming Language :: Python :: 3 :: Only
Classifier: Topic :: Utilities
Requires-Python: >=3
License-File: LICENSE
Requires-Dist: requests
